feffery_leaflet_components/EsriTiledMapLayer.py
feffery_leaflet_components/Fragment.py
feffery_leaflet_components/LeafletAntPath.py
feffery_leaflet_components/LeafletCircle.py
feffery_leaflet_components/LeafletCircleMarker.py
feffery_leaflet_components/LeafletDomWrapper.py
feffery_leaflet_components/LeafletExport.py
feffery_leaflet_components/LeafletFeatureGroup.py
feffery_leaflet_components/LeafletFlowLayer.py
feffery_leaflet_components/LeafletFullscreenControl.py
feffery_leaflet_components/LeafletGeoJSON.py
feffery_leaflet_components/LeafletHeatMap.py
feffery_leaflet_components/LeafletImageOverlay.py
feffery_leaflet_components/LeafletLayerGroup.py
feffery_leaflet_components/LeafletMap.py
feffery_leaflet_components/LeafletMapAction.py
feffery_leaflet_components/LeafletMapListener.py
feffery_leaflet_components/LeafletMapProvider.py
feffery_leaflet_components/LeafletMapSync.py
feffery_leaflet_components/LeafletMarker.py
feffery_leaflet_components/LeafletMiniMap.py
feffery_leaflet_components/LeafletPolygon.py
feffery_leaflet_components/LeafletPolyline.py
feffery_leaflet_components/LeafletPopup.py
feffery_leaflet_components/LeafletRectangle.py
feffery_leaflet_components/LeafletStaticHeatMap.py
feffery_leaflet_components/LeafletSuperCluster.py
feffery_leaflet_components/LeafletTileLayer.py
feffery_leaflet_components/LeafletTileSelect.py
feffery_leaflet_components/LeafletTooltip.py
feffery_leaflet_components/LeafletVectorTile.py
feffery_leaflet_components/MapProvider.py
feffery_leaflet_components/__init__.py
feffery_leaflet_components/_imports_.py
feffery_leaflet_components/alias.py
feffery_leaflet_components/coloring_utils.py
feffery_leaflet_components/feffery_leaflet_components.min.js
feffery_leaflet_components/feffery_leaflet_components.min.js.LICENSE.txt
feffery_leaflet_components/feffery_leaflet_components.min.js.map
feffery_leaflet_components/geometry_utils.py
feffery_leaflet_components/metadata.json
feffery_leaflet_components/package-info.json
feffery_leaflet_components-0.2.3.dist-info/licenses/LICENSE
feffery_leaflet_components-0.2.3.dist-info/METADATA
feffery_leaflet_components-0.2.3.dist-info/WHEEL
feffery_leaflet_components-0.2.3.dist-info/top_level.txt
feffery_leaflet_components-0.2.3.dist-info/RECORD
