Metadata-Version: 2.4
Name: feffery_leaflet_components
Version: 0.2.3
Summary: Best implementation of Leaflet in Plotly Dash.
Home-page: https://github.com/CNFeffery/feffery-leaflet-components
Author: CNFeffery <fefferypzy@gmail.com>
Author-email: fefferypzy@gmail.com
License: MIT
Classifier: Framework :: Dash
License-File: LICENSE
Requires-Dist: dm-tree>=0.1.7
Requires-Dist: dash>=3.1.1
Dynamic: author
Dynamic: author-email
Dynamic: classifier
Dynamic: description
Dynamic: description-content-type
Dynamic: home-page
Dynamic: license
Dynamic: license-file
Dynamic: requires-dist
Dynamic: summary
